{
  "domain": "en.wikipedia.org", 
  "json_dict": null, 
  "banned_by": null, 
  "media_embed": {}, 
  "subreddit": "todayilearned", 
  "selftext_html": null, 
  "selftext": "", 
  "likes": null, 
  "suggested_sort": null, 
  "user_reports": [], 
  "secure_media": null, 
  "link_flair_text": null, 
  "id": "1u1llp", 
  "gilded": 0, 
  "archived": true, 
  "clicked": false, 
  "report_reasons": null, 
  "author": "None", 
  "media": null, 
  "score": 2753, 
  "approved_by": null, 
  "over_18": false, 
  "hidden": false, 
  "thumbnail": "http://c.thumbs.redditmedia.com/a3iCx6CtWH1e9JbJ.jpg", 
  "subreddit_id": "t5_2qqjc", 
  "edited": false, 
  "link_flair_css_class": null, 
  "author_flair_css_class": null, 
  "downs": 0, 
  "mod_reports": [], 
  "secure_media_embed": {}, 
  "saved": false, 
  "has_fetched": true, 
  "is_self": false, 
  "name": "t3_1u1llp", 
  "permalink": "http://www.reddit.com/r/todayilearned/comments/1u1llp/til_that_the_artificial_sweetener_sucralose/", 
  "stickied": false, 
  "created": 1388438588.0, 
  "url": "http://en.wikipedia.org/wiki/Sucralose#History", 
  "author_flair_text": null, 
  "title": "TIL that the artificial sweetener Sucralose (Splenda) was discovered when a researcher misheard a command to \"Test this chemical\" as \"taste this chemical\".", 
  "created_utc": 1388438588.0, 
  "ups": 2753, 
  "upvote_ratio": 0.95, 
  "num_comments": 438, 
  "visited": false, 
  "num_reports": null, 
  "distinguished": null
}