{
  "domain": "en.wikipedia.org", 
  "json_dict": null, 
  "banned_by": null, 
  "media_embed": {}, 
  "subreddit": "todayilearned", 
  "selftext_html": null, 
  "selftext": "", 
  "likes": null, 
  "suggested_sort": null, 
  "user_reports": [], 
  "secure_media": null, 
  "link_flair_text": null, 
  "id": "1uvueq", 
  "gilded": 0, 
  "archived": true, 
  "clicked": false, 
  "report_reasons": null, 
  "author": "1AwkwardPotato", 
  "media": null, 
  "score": 2147, 
  "approved_by": null, 
  "over_18": false, 
  "hidden": false, 
  "thumbnail": "http://a.thumbs.redditmedia.com/ll4XWem_Q67fMSS6.jpg", 
  "subreddit_id": "t5_2qqjc", 
  "edited": false, 
  "link_flair_css_class": null, 
  "author_flair_css_class": null, 
  "downs": 0, 
  "mod_reports": [], 
  "secure_media_embed": {}, 
  "saved": false, 
  "has_fetched": true, 
  "is_self": false, 
  "name": "t3_1uvueq", 
  "permalink": "http://www.reddit.com/r/todayilearned/comments/1uvueq/til_that_a_dutch_athlete_was_banned_from/", 
  "stickied": false, 
  "created": 1389365882.0, 
  "url": "http://en.wikipedia.org/wiki/Foekje_Dillema", 
  "author_flair_text": null, 
  "title": "TIL that a Dutch athlete was banned from competing (for life) after refusing a sex test in 1950. After her death in 2007, an autopsy discovered a Y chromosome in her DNA, suggesting she was a genetic mosaic...", 
  "created_utc": 1389365882.0, 
  "ups": 2147, 
  "upvote_ratio": 0.92, 
  "num_comments": 511, 
  "visited": false, 
  "num_reports": null, 
  "distinguished": null
}