{
  "domain": "en.wikipedia.org", 
  "json_dict": null, 
  "banned_by": null, 
  "media_embed": {}, 
  "subreddit": "todayilearned", 
  "selftext_html": null, 
  "selftext": "", 
  "likes": null, 
  "suggested_sort": null, 
  "user_reports": [], 
  "secure_media": null, 
  "link_flair_text": "Try r/quotes? ", 
  "id": "1v668d", 
  "gilded": 0, 
  "archived": true, 
  "clicked": false, 
  "report_reasons": null, 
  "author": "churnice", 
  "media": null, 
  "score": 1173, 
  "approved_by": null, 
  "over_18": false, 
  "hidden": false, 
  "thumbnail": "http://a.thumbs.redditmedia.com/gPPyASB9mZPFGu4H.jpg", 
  "subreddit_id": "t5_2qqjc", 
  "edited": false, 
  "link_flair_css_class": "", 
  "author_flair_css_class": null, 
  "downs": 0, 
  "mod_reports": [], 
  "secure_media_embed": {}, 
  "saved": false, 
  "has_fetched": true, 
  "is_self": false, 
  "name": "t3_1v668d", 
  "permalink": "http://www.reddit.com/r/todayilearned/comments/1v668d/til_that_eric_clapton_said_about_jimi_hendrix/", 
  "stickied": false, 
  "created": 1389677254.0, 
  "url": "http://en.wikipedia.org/wiki/The_Jimi_Hendrix_Experience", 
  "author_flair_text": null, 
  "title": "TIL that Eric Clapton said about Jimi Hendrix, \"Pete Townshend and I went to see him play. I thought that was it, the game was up for all of us, we may as well pack it in.\"", 
  "created_utc": 1389677254.0, 
  "ups": 1173, 
  "upvote_ratio": 0.89, 
  "num_comments": 109, 
  "visited": false, 
  "num_reports": null, 
  "distinguished": null
}