{
  "domain": "en.wikipedia.org", 
  "json_dict": null, 
  "banned_by": null, 
  "media_embed": {}, 
  "subreddit": "todayilearned", 
  "selftext_html": null, 
  "selftext": "", 
  "likes": null, 
  "suggested_sort": null, 
  "user_reports": [], 
  "secure_media": null, 
  "link_flair_text": null, 
  "id": "1vtoqf", 
  "gilded": 0, 
  "archived": true, 
  "clicked": false, 
  "report_reasons": null, 
  "author": "JustAnAverageUser", 
  "media": null, 
  "score": 1507, 
  "approved_by": null, 
  "over_18": false, 
  "hidden": false, 
  "thumbnail": "http://a.thumbs.redditmedia.com/zB28jZ-EWiT47sCZ.jpg", 
  "subreddit_id": "t5_2qqjc", 
  "edited": false, 
  "link_flair_css_class": null, 
  "author_flair_css_class": null, 
  "downs": 0, 
  "mod_reports": [], 
  "secure_media_embed": {}, 
  "saved": false, 
  "has_fetched": true, 
  "is_self": false, 
  "name": "t3_1vtoqf", 
  "permalink": "http://www.reddit.com/r/todayilearned/comments/1vtoqf/til_oreos_are_actually_a_knockoff_of_a_cookie/", 
  "stickied": false, 
  "created": 1390363207.0, 
  "url": "http://en.wikipedia.org/wiki/Hydrox", 
  "author_flair_text": null, 
  "title": "TIL Oreos are actually a knock-off of a cookie brand called Hydrox that was created 4 years before the Oreo. People soon assumed Hydrox was the knock-off as Oreos became immensely popular.", 
  "created_utc": 1390363207.0, 
  "ups": 1507, 
  "upvote_ratio": 0.9, 
  "num_comments": 151, 
  "visited": false, 
  "num_reports": null, 
  "distinguished": null
}