{
  "domain": "en.wikipedia.org", 
  "json_dict": null, 
  "banned_by": null, 
  "media_embed": {}, 
  "subreddit": "todayilearned", 
  "selftext_html": null, 
  "selftext": "", 
  "likes": null, 
  "suggested_sort": null, 
  "user_reports": [], 
  "secure_media": null, 
  "link_flair_text": null, 
  "id": "1phmmb", 
  "gilded": 0, 
  "archived": true, 
  "clicked": false, 
  "report_reasons": null, 
  "author": "AVA711", 
  "media": null, 
  "score": 1971, 
  "approved_by": null, 
  "over_18": false, 
  "hidden": false, 
  "thumbnail": "http://e.thumbs.redditmedia.com/kxC9SHZUWN7rJwYR.jpg", 
  "subreddit_id": "t5_2qqjc", 
  "edited": false, 
  "link_flair_css_class": null, 
  "author_flair_css_class": null, 
  "downs": 0, 
  "mod_reports": [], 
  "secure_media_embed": {}, 
  "saved": false, 
  "has_fetched": true, 
  "is_self": false, 
  "name": "t3_1phmmb", 
  "permalink": "http://www.reddit.com/r/todayilearned/comments/1phmmb/til_during_wwii_when_hitler_visited_paris_the/", 
  "stickied": false, 
  "created": 1383082748.0, 
  "url": "http://en.wikipedia.org/wiki/Eiffel_Tower#Subsequent_events", 
  "author_flair_text": null, 
  "title": "TIL During WWII when Hitler visited Paris, the French cut the lift cables on the Eiffel Tower so that Hitler would have to climb the steps if he wanted to visit the summit. Hitler never went on the Eiffel Tower and it has been said that Hitler conquered France, but never conquered the Eiffel Tower.", 
  "created_utc": 1383079148.0, 
  "ups": 1971, 
  "upvote_ratio": 0.9, 
  "num_comments": 1228, 
  "visited": false, 
  "num_reports": null, 
  "distinguished": null
}