{
  "domain": "en.wikipedia.org", 
  "json_dict": null, 
  "banned_by": null, 
  "media_embed": {}, 
  "subreddit": "todayilearned", 
  "selftext_html": null, 
  "selftext": "", 
  "likes": null, 
  "suggested_sort": null, 
  "user_reports": [], 
  "secure_media": null, 
  "link_flair_text": null, 
  "id": "1fzh2w", 
  "gilded": 0, 
  "archived": true, 
  "clicked": false, 
  "report_reasons": null, 
  "author": "ThanatosK", 
  "media": null, 
  "score": 1984, 
  "approved_by": null, 
  "over_18": false, 
  "hidden": false, 
  "thumbnail": "http://f.thumbs.redditmedia.com/27XsQNFL9d6UKjW_.jpg", 
  "subreddit_id": "t5_2qqjc", 
  "edited": false, 
  "link_flair_css_class": null, 
  "author_flair_css_class": null, 
  "downs": 0, 
  "mod_reports": [], 
  "secure_media_embed": {}, 
  "saved": false, 
  "has_fetched": true, 
  "is_self": false, 
  "name": "t3_1fzh2w", 
  "permalink": "http://www.reddit.com/r/todayilearned/comments/1fzh2w/til_michael_keaton_is_a_screen_name_his_legal/", 
  "stickied": false, 
  "created": 1370796456.0, 
  "url": "http://en.wikipedia.org/wiki/Michael_Keaton#Early_career", 
  "author_flair_text": null, 
  "title": "TIL Michael Keaton is a screen name, his legal name is still Michael Douglas, but can't be used due to SAG rules.", 
  "created_utc": 1370792856.0, 
  "ups": 1984, 
  "upvote_ratio": 0.9, 
  "num_comments": 358, 
  "visited": false, 
  "num_reports": null, 
  "distinguished": null
}