{
  "domain": "en.wikipedia.org", 
  "json_dict": null, 
  "banned_by": null, 
  "media_embed": {}, 
  "subreddit": "todayilearned", 
  "selftext_html": null, 
  "selftext": "", 
  "likes": null, 
  "suggested_sort": null, 
  "user_reports": [], 
  "secure_media": null, 
  "link_flair_text": null, 
  "id": "15tnpt", 
  "gilded": 0, 
  "archived": true, 
  "clicked": false, 
  "report_reasons": null, 
  "author": "beach4k", 
  "media": null, 
  "score": 1999, 
  "approved_by": null, 
  "over_18": false, 
  "hidden": false, 
  "thumbnail": "http://f.thumbs.redditmedia.com/7T7in252gp_Jdw7Y.jpg", 
  "subreddit_id": "t5_2qqjc", 
  "edited": false, 
  "link_flair_css_class": null, 
  "author_flair_css_class": null, 
  "downs": 0, 
  "mod_reports": [], 
  "secure_media_embed": {}, 
  "saved": false, 
  "has_fetched": true, 
  "is_self": false, 
  "name": "t3_15tnpt", 
  "permalink": "http://www.reddit.com/r/todayilearned/comments/15tnpt/til_the_yakuza_operate_openly_in_japan_they_have/", 
  "stickied": false, 
  "created": 1357131174.0, 
  "url": "http://en.wikipedia.org/wiki/Yakuza#Current_activities", 
  "author_flair_text": null, 
  "title": "TIL the Yakuza operate openly in Japan: they have offices, make charitable donations, and even have large investments in mainstream companies", 
  "created_utc": 1357131174.0, 
  "ups": 1999, 
  "upvote_ratio": 0.93, 
  "num_comments": 1257, 
  "visited": false, 
  "num_reports": null, 
  "distinguished": null
}