{
  "domain": "en.wikipedia.org", 
  "json_dict": null, 
  "banned_by": null, 
  "media_embed": {}, 
  "subreddit": "todayilearned", 
  "selftext_html": null, 
  "selftext": "", 
  "likes": null, 
  "suggested_sort": null, 
  "user_reports": [], 
  "secure_media": null, 
  "link_flair_text": null, 
  "id": "17d8fn", 
  "gilded": 0, 
  "archived": true, 
  "clicked": false, 
  "report_reasons": null, 
  "author": "ChinatownHustler", 
  "media": null, 
  "score": 1529, 
  "approved_by": null, 
  "over_18": false, 
  "hidden": false, 
  "thumbnail": "http://d.thumbs.redditmedia.com/yJie69-odE2Bu9uu.jpg", 
  "subreddit_id": "t5_2qqjc", 
  "edited": false, 
  "link_flair_css_class": null, 
  "author_flair_css_class": null, 
  "downs": 0, 
  "mod_reports": [], 
  "secure_media_embed": {}, 
  "saved": false, 
  "has_fetched": true, 
  "is_self": false, 
  "name": "t3_17d8fn", 
  "permalink": "http://www.reddit.com/r/todayilearned/comments/17d8fn/til_that_there_is_a_feature_length_anime_movie/", 
  "stickied": false, 
  "created": 1359292713.0, 
  "url": "http://en.wikipedia.org/wiki/Interstella_5555:_The_5tory_of_the_5ecret_5tar_5ystem", 
  "author_flair_text": null, 
  "title": "TIL that there is a feature length anime movie based on the music of Daft Punk. It contains no dialogue or sound effects and was called \"the best animated movie made in 2003.\"", 
  "created_utc": 1359292713.0, 
  "ups": 1529, 
  "upvote_ratio": 0.86, 
  "num_comments": 325, 
  "visited": false, 
  "num_reports": null, 
  "distinguished": null
}