{
  "domain": "en.wikipedia.org", 
  "json_dict": null, 
  "banned_by": null, 
  "media_embed": {}, 
  "subreddit": "todayilearned", 
  "selftext_html": null, 
  "selftext": "", 
  "likes": null, 
  "suggested_sort": null, 
  "user_reports": [], 
  "secure_media": null, 
  "link_flair_text": null, 
  "id": "1w6l42", 
  "gilded": 0, 
  "archived": true, 
  "clicked": false, 
  "report_reasons": null, 
  "author": "Trentious", 
  "media": null, 
  "score": 1678, 
  "approved_by": null, 
  "over_18": false, 
  "hidden": false, 
  "thumbnail": "http://a.thumbs.redditmedia.com/uMiXh-35MvBdwsq0.jpg", 
  "subreddit_id": "t5_2qqjc", 
  "edited": false, 
  "link_flair_css_class": null, 
  "author_flair_css_class": null, 
  "downs": 0, 
  "mod_reports": [], 
  "secure_media_embed": {}, 
  "saved": false, 
  "has_fetched": true, 
  "is_self": false, 
  "name": "t3_1w6l42", 
  "permalink": "http://www.reddit.com/r/todayilearned/comments/1w6l42/til_that_potentially_35_million_people_have_been/", 
  "stickied": false, 
  "created": 1390725632.0, 
  "url": "http://en.wikipedia.org/wiki/Human_rights_in_North_Korea#Internment_camps_for_political_prisoners", 
  "author_flair_text": null, 
  "title": "TIL that potentially 3.5 million people have been killed so far in North Korea as a result of famine, forced labor, executions, and concentration camps.", 
  "created_utc": 1390725632.0, 
  "ups": 1678, 
  "upvote_ratio": 0.91, 
  "num_comments": 206, 
  "visited": false, 
  "num_reports": null, 
  "distinguished": null
}