{
  "domain": "en.wikipedia.org", 
  "json_dict": null, 
  "banned_by": null, 
  "media_embed": {}, 
  "subreddit": "todayilearned", 
  "selftext_html": null, 
  "selftext": "", 
  "likes": null, 
  "suggested_sort": null, 
  "user_reports": [], 
  "secure_media": null, 
  "link_flair_text": null, 
  "id": "1jn4hi", 
  "gilded": 0, 
  "archived": true, 
  "clicked": false, 
  "report_reasons": null, 
  "author": "None", 
  "media": null, 
  "score": 1083, 
  "approved_by": null, 
  "over_18": false, 
  "hidden": false, 
  "thumbnail": "http://a.thumbs.redditmedia.com/5qeeZwBW0sHICOhf.jpg", 
  "subreddit_id": "t5_2qqjc", 
  "edited": false, 
  "link_flair_css_class": null, 
  "author_flair_css_class": null, 
  "downs": 0, 
  "mod_reports": [], 
  "secure_media_embed": {}, 
  "saved": false, 
  "has_fetched": true, 
  "is_self": false, 
  "name": "t3_1jn4hi", 
  "permalink": "http://www.reddit.com/r/todayilearned/comments/1jn4hi/til_that_the_laws_of_war_allow_soldiers_to_wear/", 
  "stickied": false, 
  "created": 1375563803.0, 
  "url": "http://en.wikipedia.org/wiki/Rules_of_war", 
  "author_flair_text": null, 
  "title": "TIL That the Laws of War allow soldiers to wear an enemy's uniform, but does not allow them to engage in combat while wearing the uniform.", 
  "created_utc": 1375560203.0, 
  "ups": 1083, 
  "upvote_ratio": 0.94, 
  "num_comments": 143, 
  "visited": false, 
  "num_reports": null, 
  "distinguished": null
}