{
  "domain": "en.wikipedia.org", 
  "json_dict": null, 
  "banned_by": null, 
  "media_embed": {}, 
  "subreddit": "todayilearned", 
  "selftext_html": null, 
  "selftext": "", 
  "likes": null, 
  "suggested_sort": null, 
  "user_reports": [], 
  "secure_media": null, 
  "link_flair_text": "Not verifiable (1)", 
  "id": "1axro3", 
  "gilded": 0, 
  "archived": true, 
  "clicked": false, 
  "report_reasons": null, 
  "author": "saladwithaspoon", 
  "media": null, 
  "score": 2068, 
  "approved_by": null, 
  "over_18": false, 
  "hidden": false, 
  "thumbnail": "default", 
  "subreddit_id": "t5_2qqjc", 
  "edited": false, 
  "link_flair_css_class": "unverifiable", 
  "author_flair_css_class": null, 
  "downs": 0, 
  "mod_reports": [], 
  "secure_media_embed": {}, 
  "saved": false, 
  "has_fetched": true, 
  "is_self": false, 
  "name": "t3_1axro3", 
  "permalink": "http://www.reddit.com/r/todayilearned/comments/1axro3/til_there_is_a_perfectly_painless_of_killing/", 
  "stickied": false, 
  "created": 1364167979.0, 
  "url": "http://en.wikipedia.org/wiki/Nitrogen_asphyxiation", 
  "author_flair_text": null, 
  "title": "TIL there is a perfectly painless of killing someone through nitrogen asphyxiation by cutting off oxygen while still supplying nitrogen so that the body does not experience a suffocating sensation. However, this method is not used by any government as a method of capital punishment.", 
  "created_utc": 1364164379.0, 
  "ups": 2068, 
  "upvote_ratio": 0.93, 
  "num_comments": 879, 
  "visited": false, 
  "num_reports": null, 
  "distinguished": null
}