{
  "domain": "en.wikipedia.org", 
  "json_dict": null, 
  "banned_by": null, 
  "media_embed": {}, 
  "subreddit": "todayilearned", 
  "selftext_html": null, 
  "selftext": "", 
  "likes": null, 
  "suggested_sort": null, 
  "user_reports": [], 
  "secure_media": null, 
  "link_flair_text": null, 
  "id": "1j02tm", 
  "gilded": 0, 
  "archived": true, 
  "clicked": false, 
  "report_reasons": null, 
  "author": "None", 
  "media": null, 
  "score": 1697, 
  "approved_by": null, 
  "over_18": false, 
  "hidden": false, 
  "thumbnail": "http://a.thumbs.redditmedia.com/5FmT-8QGNRBGyrtf.jpg", 
  "subreddit_id": "t5_2qqjc", 
  "edited": false, 
  "link_flair_css_class": null, 
  "author_flair_css_class": null, 
  "downs": 0, 
  "mod_reports": [], 
  "secure_media_embed": {}, 
  "saved": false, 
  "has_fetched": true, 
  "is_self": false, 
  "name": "t3_1j02tm", 
  "permalink": "http://www.reddit.com/r/todayilearned/comments/1j02tm/til_michael_cera_was_the_voice_of_brother_bear_in/", 
  "stickied": false, 
  "created": 1374723691.0, 
  "url": "https://en.wikipedia.org/wiki/Michael_Cera#Rise", 
  "author_flair_text": null, 
  "title": "TIL Michael Cera was the voice of Brother Bear in The Berenstain Bears animated series.", 
  "created_utc": 1374720091.0, 
  "ups": 1697, 
  "upvote_ratio": 0.88, 
  "num_comments": 58, 
  "visited": false, 
  "num_reports": null, 
  "distinguished": null
}