{
  "domain": "en.wikipedia.org", 
  "json_dict": null, 
  "banned_by": null, 
  "media_embed": {}, 
  "subreddit": "todayilearned", 
  "selftext_html": null, 
  "selftext": "", 
  "likes": null, 
  "suggested_sort": null, 
  "user_reports": [], 
  "secure_media": null, 
  "link_flair_text": null, 
  "id": "1f1r9p", 
  "gilded": 0, 
  "archived": true, 
  "clicked": false, 
  "report_reasons": null, 
  "author": "Butter_Meister", 
  "media": null, 
  "score": 1730, 
  "approved_by": null, 
  "over_18": false, 
  "hidden": false, 
  "thumbnail": "http://d.thumbs.redditmedia.com/RE9PFKISouuXAH3W.jpg", 
  "subreddit_id": "t5_2qqjc", 
  "edited": false, 
  "link_flair_css_class": null, 
  "author_flair_css_class": null, 
  "downs": 0, 
  "mod_reports": [], 
  "secure_media_embed": {}, 
  "saved": false, 
  "has_fetched": true, 
  "is_self": false, 
  "name": "t3_1f1r9p", 
  "permalink": "http://www.reddit.com/r/todayilearned/comments/1f1r9p/til_drinking_was_allowed_in_bars_in_atlanta/", 
  "stickied": false, 
  "created": 1369520510.0, 
  "url": "http://en.wikipedia.org/wiki/Underground_Atlanta#Rediscovery_and_restoration", 
  "author_flair_text": null, 
  "title": "TIL drinking was allowed in bars in Atlanta, Georgia in 1969 only if men were wearing suits and ties.", 
  "created_utc": 1369516910.0, 
  "ups": 1730, 
  "upvote_ratio": 0.94, 
  "num_comments": 159, 
  "visited": false, 
  "num_reports": null, 
  "distinguished": null
}