{
  "domain": "en.wikipedia.org", 
  "json_dict": null, 
  "banned_by": null, 
  "media_embed": {}, 
  "subreddit": "todayilearned", 
  "selftext_html": null, 
  "selftext": "", 
  "likes": null, 
  "suggested_sort": null, 
  "user_reports": [], 
  "secure_media": null, 
  "link_flair_text": null, 
  "id": "1fgy7u", 
  "gilded": 0, 
  "archived": true, 
  "clicked": false, 
  "report_reasons": null, 
  "author": "TRAVICEW", 
  "media": null, 
  "score": 1839, 
  "approved_by": null, 
  "over_18": false, 
  "hidden": false, 
  "thumbnail": "http://a.thumbs.redditmedia.com/_ng0QDfwdieQkB1T.jpg", 
  "subreddit_id": "t5_2qqjc", 
  "edited": false, 
  "link_flair_css_class": null, 
  "author_flair_css_class": null, 
  "downs": 0, 
  "mod_reports": [], 
  "secure_media_embed": {}, 
  "saved": false, 
  "has_fetched": true, 
  "is_self": false, 
  "name": "t3_1fgy7u", 
  "permalink": "http://www.reddit.com/r/todayilearned/comments/1fgy7u/til_the_first_man_to_fly_and_the_first_man_to/", 
  "stickied": false, 
  "created": 1370109214.0, 
  "url": "https://en.wikipedia.org/wiki/Orville_Wright", 
  "author_flair_text": null, 
  "title": "TIL The first man to fly and the first man to walk on the moon were alive at the same time. Neil Armstrong was 17 when Orville Wright died.", 
  "created_utc": 1370105614.0, 
  "ups": 1839, 
  "upvote_ratio": 0.9, 
  "num_comments": 737, 
  "visited": false, 
  "num_reports": null, 
  "distinguished": null
}