{
  "domain": "en.wikipedia.org", 
  "json_dict": null, 
  "banned_by": null, 
  "media_embed": {}, 
  "subreddit": "todayilearned", 
  "selftext_html": null, 
  "selftext": "", 
  "likes": null, 
  "suggested_sort": null, 
  "user_reports": [], 
  "secure_media": null, 
  "link_flair_text": null, 
  "id": "1lunpe", 
  "gilded": 0, 
  "archived": true, 
  "clicked": false, 
  "report_reasons": null, 
  "author": "fault_6", 
  "media": null, 
  "score": 1227, 
  "approved_by": null, 
  "over_18": false, 
  "hidden": false, 
  "thumbnail": "default", 
  "subreddit_id": "t5_2qqjc", 
  "edited": false, 
  "link_flair_css_class": null, 
  "author_flair_css_class": null, 
  "downs": 0, 
  "mod_reports": [], 
  "secure_media_embed": {}, 
  "saved": false, 
  "has_fetched": true, 
  "is_self": false, 
  "name": "t3_1lunpe", 
  "permalink": "http://www.reddit.com/r/todayilearned/comments/1lunpe/til_the_son_of_benny_hinn_joshua_hinn_along_with/", 
  "stickied": false, 
  "created": 1378477361.0, 
  "url": "http://en.wikipedia.org/wiki/Benny_Hinn#Son.27s_Alleged_Crime", 
  "author_flair_text": null, 
  "title": "TIL the son of Benny Hinn - Joshua Hinn - along with his body guards beat the shit out of a deaf and dumb man for trying to walk to the stage for prayer. Charges were later dropped for a \"large sum of money.\"", 
  "created_utc": 1378473761.0, 
  "ups": 1227, 
  "upvote_ratio": 0.88, 
  "num_comments": 122, 
  "visited": false, 
  "num_reports": null, 
  "distinguished": null
}