{
  "domain": "en.wikipedia.org", 
  "json_dict": null, 
  "banned_by": null, 
  "media_embed": {}, 
  "subreddit": "todayilearned", 
  "selftext_html": null, 
  "selftext": "", 
  "likes": null, 
  "suggested_sort": null, 
  "user_reports": [], 
  "secure_media": null, 
  "link_flair_text": null, 
  "id": "1zyo19", 
  "gilded": 0, 
  "archived": true, 
  "clicked": false, 
  "report_reasons": null, 
  "author": "sphinxv1337", 
  "media": null, 
  "score": 2415, 
  "approved_by": null, 
  "over_18": false, 
  "hidden": false, 
  "thumbnail": "default", 
  "subreddit_id": "t5_2qqjc", 
  "edited": false, 
  "link_flair_css_class": null, 
  "author_flair_css_class": null, 
  "downs": 0, 
  "mod_reports": [], 
  "secure_media_embed": {}, 
  "saved": false, 
  "has_fetched": true, 
  "is_self": false, 
  "name": "t3_1zyo19", 
  "permalink": "http://www.reddit.com/r/todayilearned/comments/1zyo19/til_for_10_years_in_the_uk_there_was_a_pro/", 
  "stickied": false, 
  "created": 1394372319.0, 
  "url": "http://en.wikipedia.org/wiki/Paedophile_Information_Exchange", 
  "author_flair_text": null, 
  "title": "TIL for 10 years in the UK, there was a pro paedophile group that campaigned for the age of consent to be removed/lowered to just 4 years.", 
  "created_utc": 1394368719.0, 
  "ups": 2415, 
  "upvote_ratio": 0.91, 
  "num_comments": 1154, 
  "visited": false, 
  "num_reports": null, 
  "distinguished": null
}