{
  "domain": "en.wikipedia.org", 
  "json_dict": null, 
  "banned_by": null, 
  "media_embed": {}, 
  "subreddit": "todayilearned", 
  "selftext_html": null, 
  "selftext": "", 
  "likes": null, 
  "suggested_sort": null, 
  "user_reports": [], 
  "secure_media": null, 
  "link_flair_text": null, 
  "id": "1ew9r4", 
  "gilded": 0, 
  "archived": true, 
  "clicked": false, 
  "report_reasons": null, 
  "author": "None", 
  "media": null, 
  "score": 1603, 
  "approved_by": null, 
  "over_18": false, 
  "hidden": false, 
  "thumbnail": "http://e.thumbs.redditmedia.com/Dxe77YSonKGBBtyv.jpg", 
  "subreddit_id": "t5_2qqjc", 
  "edited": false, 
  "link_flair_css_class": null, 
  "author_flair_css_class": null, 
  "downs": 0, 
  "mod_reports": [], 
  "secure_media_embed": {}, 
  "saved": false, 
  "has_fetched": true, 
  "is_self": false, 
  "name": "t3_1ew9r4", 
  "permalink": "http://www.reddit.com/r/todayilearned/comments/1ew9r4/til_edgar_mitchell_the_sixth_person_to_walk_on/", 
  "stickied": false, 
  "created": 1369309248.0, 
  "url": "https://en.wikipedia.org/wiki/Edgar_Mitchell#Views_on_UFOs", 
  "author_flair_text": null, 
  "title": "TIL Edgar Mitchell, the sixth person to walk on the moon, has claimed that \"aliens have contacted humans several times\" on Kerrang radio in 2008", 
  "created_utc": 1369305648.0, 
  "ups": 1603, 
  "upvote_ratio": 0.92, 
  "num_comments": 476, 
  "visited": false, 
  "num_reports": null, 
  "distinguished": null
}