{
  "domain": "en.wikipedia.org", 
  "json_dict": null, 
  "banned_by": null, 
  "media_embed": {}, 
  "subreddit": "todayilearned", 
  "selftext_html": null, 
  "selftext": "", 
  "likes": null, 
  "suggested_sort": null, 
  "user_reports": [], 
  "secure_media": null, 
  "link_flair_text": null, 
  "id": "1zfze6", 
  "gilded": 0, 
  "archived": true, 
  "clicked": false, 
  "report_reasons": null, 
  "author": "Zlor", 
  "media": null, 
  "score": 2533, 
  "approved_by": null, 
  "over_18": false, 
  "hidden": false, 
  "thumbnail": "http://a.thumbs.redditmedia.com/hUMc2Rll8KvxnMbf.jpg", 
  "subreddit_id": "t5_2qqjc", 
  "edited": false, 
  "link_flair_css_class": null, 
  "author_flair_css_class": null, 
  "downs": 0, 
  "mod_reports": [], 
  "secure_media_embed": {}, 
  "saved": false, 
  "has_fetched": true, 
  "is_self": false, 
  "name": "t3_1zfze6", 
  "permalink": "http://www.reddit.com/r/todayilearned/comments/1zfze6/til_that_bart_simpsons_hit_song_do_the_bartman/", 
  "stickied": false, 
  "created": 1393864652.0, 
  "url": "http://en.wikipedia.org/wiki/Do_the_bartman", 
  "author_flair_text": null, 
  "title": "TIL that Bart Simpsons hit song \"Do the Bartman\" was written by massive Simpsons fan, Michael Jackson.", 
  "created_utc": 1393864652.0, 
  "ups": 2533, 
  "upvote_ratio": 0.93, 
  "num_comments": 146, 
  "visited": false, 
  "num_reports": null, 
  "distinguished": null
}