{
  "domain": "en.wikipedia.org", 
  "json_dict": null, 
  "banned_by": null, 
  "media_embed": {}, 
  "subreddit": "todayilearned", 
  "selftext_html": null, 
  "selftext": "", 
  "likes": null, 
  "suggested_sort": null, 
  "user_reports": [], 
  "secure_media": null, 
  "link_flair_text": null, 
  "id": "2krz19", 
  "gilded": 0, 
  "archived": true, 
  "clicked": false, 
  "report_reasons": null, 
  "author": "shaggorama", 
  "media": null, 
  "score": 3157, 
  "approved_by": null, 
  "over_18": false, 
  "hidden": false, 
  "thumbnail": "http://b.thumbs.redditmedia.com/96rWYzvnI7XVyYoQUD4vgYqxjayKxiTn9eNhV7EsiBE.jpg", 
  "subreddit_id": "t5_2qqjc", 
  "edited": false, 
  "link_flair_css_class": null, 
  "author_flair_css_class": "points ", 
  "downs": 0, 
  "mod_reports": [], 
  "secure_media_embed": {}, 
  "saved": false, 
  "has_fetched": true, 
  "is_self": false, 
  "name": "t3_2krz19", 
  "permalink": "http://www.reddit.com/r/todayilearned/comments/2krz19/til_a_90_year_old_woman_with_no_heirs_signed_a/", 
  "stickied": false, 
  "created": 1414677056.0, 
  "url": "http://en.wikipedia.org/wiki/Jeanne_Calment#Health_and_lifestyle", 
  "author_flair_text": "1", 
  "title": "TIL a 90 year old woman with no heirs signed a contract with a 47 year old lawyer giving him her apartment upon her death, but he had to pay her a monthly allowance until she died. She outlived him and his widow continued the payments. She received approximately double the value of the apartment.", 
  "created_utc": 1414673456.0, 
  "ups": 3157, 
  "upvote_ratio": 0.9, 
  "num_comments": 1055, 
  "visited": false, 
  "num_reports": null, 
  "distinguished": null
}