{
  "domain": "en.wikipedia.org", 
  "json_dict": null, 
  "banned_by": null, 
  "media_embed": {}, 
  "subreddit": "todayilearned", 
  "selftext_html": null, 
  "selftext": "", 
  "likes": null, 
  "suggested_sort": null, 
  "user_reports": [], 
  "secure_media": null, 
  "link_flair_text": null, 
  "id": "2jiy49", 
  "gilded": 0, 
  "archived": true, 
  "clicked": false, 
  "report_reasons": null, 
  "author": "None", 
  "media": null, 
  "score": 3033, 
  "approved_by": null, 
  "over_18": false, 
  "hidden": false, 
  "thumbnail": "default", 
  "subreddit_id": "t5_2qqjc", 
  "edited": false, 
  "link_flair_css_class": null, 
  "author_flair_css_class": null, 
  "downs": 0, 
  "mod_reports": [], 
  "secure_media_embed": {}, 
  "saved": false, 
  "has_fetched": true, 
  "is_self": false, 
  "name": "t3_2jiy49", 
  "permalink": "http://www.reddit.com/r/todayilearned/comments/2jiy49/til_after_charles_roberts_executed_6_children_at/", 
  "stickied": false, 
  "created": 1413564967.0, 
  "url": "http://en.wikipedia.org/wiki/Amish_school_shooting#Amish_community_response", 
  "author_flair_text": null, 
  "title": "TIL After Charles Roberts executed 6 children at an Amish school and killed himself, the Amish community comforted the shooters family, set up a charitable fund for them, and 30 members of the Amish community attended the Charles Roberts funeral.", 
  "created_utc": 1413561367.0, 
  "ups": 3033, 
  "upvote_ratio": 0.93, 
  "num_comments": 307, 
  "visited": false, 
  "num_reports": null, 
  "distinguished": null
}