{
  "domain": "en.wikipedia.org", 
  "json_dict": null, 
  "banned_by": null, 
  "media_embed": {}, 
  "subreddit": "todayilearned", 
  "selftext_html": null, 
  "selftext": "", 
  "likes": null, 
  "suggested_sort": null, 
  "user_reports": [], 
  "secure_media": null, 
  "link_flair_text": "(R.1) Tenuous evidence", 
  "id": "2cwrfk", 
  "gilded": 0, 
  "archived": true, 
  "clicked": false, 
  "report_reasons": null, 
  "author": "PointyOintment", 
  "media": null, 
  "score": 3070, 
  "approved_by": null, 
  "over_18": false, 
  "hidden": false, 
  "thumbnail": "default", 
  "subreddit_id": "t5_2qqjc", 
  "edited": false, 
  "link_flair_css_class": "", 
  "author_flair_css_class": "points ", 
  "downs": 0, 
  "mod_reports": [], 
  "secure_media_embed": {}, 
  "saved": false, 
  "has_fetched": true, 
  "is_self": false, 
  "name": "t3_2cwrfk", 
  "permalink": "http://www.reddit.com/r/todayilearned/comments/2cwrfk/til_that_american_judges_can_kick_out_jurors_whom/", 
  "stickied": false, 
  "created": 1407442195.0, 
  "url": "https://en.wikipedia.org/wiki/Jury#Jury_nullification", 
  "author_flair_text": "2", 
  "title": "TIL that American judges can kick out jurors whom they believe are aware of the jury's ability to nullify laws", 
  "created_utc": 1407438595.0, 
  "ups": 3070, 
  "upvote_ratio": 0.94, 
  "num_comments": 1208, 
  "visited": false, 
  "num_reports": null, 
  "distinguished": null
}