{
  "domain": "en.wikipedia.org", 
  "json_dict": null, 
  "banned_by": null, 
  "media_embed": {}, 
  "subreddit": "todayilearned", 
  "selftext_html": null, 
  "selftext": "", 
  "likes": null, 
  "suggested_sort": null, 
  "user_reports": [], 
  "secure_media": null, 
  "link_flair_text": null, 
  "id": "24gxxz", 
  "gilded": 0, 
  "archived": true, 
  "clicked": false, 
  "report_reasons": null, 
  "author": "None", 
  "media": null, 
  "score": 1252, 
  "approved_by": null, 
  "over_18": false, 
  "hidden": false, 
  "thumbnail": "default", 
  "subreddit_id": "t5_2qqjc", 
  "edited": false, 
  "link_flair_css_class": null, 
  "author_flair_css_class": null, 
  "downs": 0, 
  "mod_reports": [], 
  "secure_media_embed": {}, 
  "saved": false, 
  "has_fetched": true, 
  "is_self": false, 
  "name": "t3_24gxxz", 
  "permalink": "http://www.reddit.com/r/todayilearned/comments/24gxxz/til_mozart_composed_the_overture_to_his_opera_don/", 
  "stickied": false, 
  "created": 1398968506.0, 
  "url": "http://en.wikipedia.org/wiki/Don_Giovanni#Composition_and_premieres", 
  "author_flair_text": null, 
  "title": "TIL Mozart composed the overture to his opera \"Don Giovanni\" the morning of the premiere", 
  "created_utc": 1398964906.0, 
  "ups": 1252, 
  "upvote_ratio": 0.93, 
  "num_comments": 86, 
  "visited": false, 
  "num_reports": null, 
  "distinguished": null
}