{
  "domain": "en.wikipedia.org", 
  "json_dict": null, 
  "banned_by": null, 
  "media_embed": {}, 
  "subreddit": "todayilearned", 
  "selftext_html": null, 
  "selftext": "", 
  "likes": null, 
  "suggested_sort": null, 
  "user_reports": [], 
  "secure_media": null, 
  "link_flair_text": "word for word repost", 
  "id": "24pax2", 
  "gilded": 0, 
  "archived": true, 
  "clicked": false, 
  "report_reasons": null, 
  "author": "mrredditkarma", 
  "media": null, 
  "score": 3249, 
  "approved_by": null, 
  "over_18": false, 
  "hidden": false, 
  "thumbnail": "default", 
  "subreddit_id": "t5_2qqjc", 
  "edited": false, 
  "link_flair_css_class": "", 
  "author_flair_css_class": null, 
  "downs": 0, 
  "mod_reports": [], 
  "secure_media_embed": {}, 
  "saved": false, 
  "has_fetched": true, 
  "is_self": false, 
  "name": "t3_24pax2", 
  "permalink": "http://www.reddit.com/r/todayilearned/comments/24pax2/til_that_in_1945_dwight_d_einsenhower_predicted/", 
  "stickied": false, 
  "created": 1399225459.0, 
  "url": "https://en.wikipedia.org/wiki/Holocaust_denial#Attempts_at_concealment_by_perpetrators", 
  "author_flair_text": null, 
  "title": "TIL that in 1945, Dwight D. Einsenhower predicted that people would try to dispel the holocaust as a falsehood, and ordered innumerable pictures to be taken of the Nazi crimes to hinder any such attempts", 
  "created_utc": 1399221859.0, 
  "ups": 3249, 
  "upvote_ratio": 0.94, 
  "num_comments": 548, 
  "visited": false, 
  "num_reports": null, 
  "distinguished": null
}