{
  "domain": "en.wikipedia.org", 
  "json_dict": null, 
  "banned_by": null, 
  "media_embed": {}, 
  "subreddit": "todayilearned", 
  "selftext_html": null, 
  "selftext": "", 
  "likes": null, 
  "suggested_sort": null, 
  "user_reports": [], 
  "secure_media": null, 
  "link_flair_text": "(R.5) Misleading", 
  "id": "238awo", 
  "gilded": 0, 
  "archived": true, 
  "clicked": false, 
  "report_reasons": null, 
  "author": "jamese1313", 
  "media": null, 
  "score": 1726, 
  "approved_by": null, 
  "over_18": false, 
  "hidden": false, 
  "thumbnail": "default", 
  "subreddit_id": "t5_2qqjc", 
  "edited": false, 
  "link_flair_css_class": "", 
  "author_flair_css_class": null, 
  "downs": 0, 
  "mod_reports": [], 
  "secure_media_embed": {}, 
  "saved": false, 
  "has_fetched": true, 
  "is_self": false, 
  "name": "t3_238awo", 
  "permalink": "http://www.reddit.com/r/todayilearned/comments/238awo/til_of_the_solomon_curve_the_safest_speed_to/", 
  "stickied": false, 
  "created": 1397699413.0, 
  "url": "http://en.wikipedia.org/wiki/Solomon_curve#The_original_research", 
  "author_flair_text": null, 
  "title": "TIL of the Solomon curve. The safest speed to travel at is five miles over the speed limit.", 
  "created_utc": 1397695813.0, 
  "ups": 1726, 
  "upvote_ratio": 0.8, 
  "num_comments": 446, 
  "visited": false, 
  "num_reports": null, 
  "distinguished": null
}