{
  "domain": "en.wikipedia.org", 
  "json_dict": null, 
  "banned_by": null, 
  "media_embed": {}, 
  "subreddit": "todayilearned", 
  "selftext_html": null, 
  "selftext": "", 
  "likes": null, 
  "suggested_sort": null, 
  "user_reports": [], 
  "secure_media": null, 
  "link_flair_text": null, 
  "id": "24j4py", 
  "gilded": 0, 
  "archived": true, 
  "clicked": false, 
  "report_reasons": null, 
  "author": "Stalpph", 
  "media": null, 
  "score": 2840, 
  "approved_by": null, 
  "over_18": false, 
  "hidden": false, 
  "thumbnail": "http://c.thumbs.redditmedia.com/UxbiKlTvi8iTk9ED.jpg", 
  "subreddit_id": "t5_2qqjc", 
  "edited": false, 
  "link_flair_css_class": null, 
  "author_flair_css_class": null, 
  "downs": 0, 
  "mod_reports": [], 
  "secure_media_embed": {}, 
  "saved": false, 
  "has_fetched": true, 
  "is_self": false, 
  "name": "t3_24j4py", 
  "permalink": "http://www.reddit.com/r/todayilearned/comments/24j4py/til_for_the_guinness_world_records_it_is_required/", 
  "stickied": false, 
  "created": 1399028663.0, 
  "url": "http://en.wikipedia.org/wiki/Guinness_World_Record#Ethical_issues_and_safety_concerns", 
  "author_flair_text": null, 
  "title": "TIL For the Guinness World Records, it is required in the guidelines of all \"large food\" type records that the item be fully edible, and distributed to the public for consumption, to prevent food wastage.", 
  "created_utc": 1399025063.0, 
  "ups": 2840, 
  "upvote_ratio": 0.94, 
  "num_comments": 259, 
  "visited": false, 
  "num_reports": null, 
  "distinguished": null
}