{
  "domain": "en.wikipedia.org", 
  "json_dict": null, 
  "banned_by": null, 
  "media_embed": {}, 
  "subreddit": "todayilearned", 
  "selftext_html": null, 
  "selftext": "", 
  "likes": null, 
  "suggested_sort": null, 
  "user_reports": [], 
  "secure_media": null, 
  "link_flair_text": null, 
  "id": "2f33qw", 
  "gilded": 0, 
  "archived": true, 
  "clicked": false, 
  "report_reasons": null, 
  "author": "NeverRainingRoses", 
  "media": null, 
  "score": 2175, 
  "approved_by": null, 
  "over_18": false, 
  "hidden": false, 
  "thumbnail": "http://b.thumbs.redditmedia.com/Lvy0bJR-6Mdw1Hr-6tM5ioYEtj2SQvquz-Vtbhw-RHQ.jpg", 
  "subreddit_id": "t5_2qqjc", 
  "edited": false, 
  "link_flair_css_class": null, 
  "author_flair_css_class": null, 
  "downs": 0, 
  "mod_reports": [], 
  "secure_media_embed": {}, 
  "saved": false, 
  "has_fetched": true, 
  "is_self": false, 
  "name": "t3_2f33qw", 
  "permalink": "http://www.reddit.com/r/todayilearned/comments/2f33qw/til_that_although_lead_paint_was_recognized_as/", 
  "stickied": false, 
  "created": 1409500678.0, 
  "url": "http://en.wikipedia.org/wiki/Lead_poisoning#History", 
  "author_flair_text": null, 
  "title": "TIL that although lead paint was recognized as toxic as early as 1897 and banned by the League of Nations in 1922, the US did not ban lead paint until 1971.", 
  "created_utc": 1409497078.0, 
  "ups": 2175, 
  "upvote_ratio": 0.94, 
  "num_comments": 158, 
  "visited": false, 
  "num_reports": null, 
  "distinguished": null
}