{
  "domain": "en.wikipedia.org", 
  "json_dict": null, 
  "banned_by": null, 
  "media_embed": {}, 
  "subreddit": "todayilearned", 
  "selftext_html": null, 
  "selftext": "", 
  "likes": null, 
  "suggested_sort": null, 
  "user_reports": [], 
  "secure_media": null, 
  "link_flair_text": null, 
  "id": "2hg9cs", 
  "gilded": 0, 
  "archived": true, 
  "clicked": false, 
  "report_reasons": null, 
  "author": "JeffRyan1", 
  "media": null, 
  "score": 1231, 
  "approved_by": null, 
  "over_18": false, 
  "hidden": false, 
  "thumbnail": "http://b.thumbs.redditmedia.com/vonrFg5nBDWAi8aHvww20Ru-mSDmLRjZ-7ALbzGUssc.jpg", 
  "subreddit_id": "t5_2qqjc", 
  "edited": false, 
  "link_flair_css_class": null, 
  "author_flair_css_class": null, 
  "downs": 0, 
  "mod_reports": [], 
  "secure_media_embed": {}, 
  "saved": false, 
  "has_fetched": true, 
  "is_self": false, 
  "name": "t3_2hg9cs", 
  "permalink": "http://www.reddit.com/r/todayilearned/comments/2hg9cs/today_i_learned_tom_and_jerry_cartoons_won_seven/", 
  "stickied": false, 
  "created": 1411672197.0, 
  "url": "http://en.wikipedia.org/wiki/Tom_and_Jerry#Filmography", 
  "author_flair_text": null, 
  "title": "Today I learned Tom and Jerry cartoons won seven Oscars, and were nominated for six more.", 
  "created_utc": 1411668597.0, 
  "ups": 1231, 
  "upvote_ratio": 0.92, 
  "num_comments": 71, 
  "visited": false, 
  "num_reports": null, 
  "distinguished": null
}