{
  "domain": "en.wikipedia.org", 
  "json_dict": null, 
  "banned_by": null, 
  "media_embed": {}, 
  "subreddit": "todayilearned", 
  "selftext_html": null, 
  "selftext": "", 
  "likes": null, 
  "suggested_sort": null, 
  "user_reports": [], 
  "secure_media": null, 
  "link_flair_text": null, 
  "id": "24pm00", 
  "gilded": 0, 
  "archived": true, 
  "clicked": false, 
  "report_reasons": null, 
  "author": "lgf92", 
  "media": null, 
  "score": 2209, 
  "approved_by": null, 
  "over_18": false, 
  "hidden": false, 
  "thumbnail": "http://c.thumbs.redditmedia.com/7MibZj4sjWHnROIh.jpg", 
  "subreddit_id": "t5_2qqjc", 
  "edited": false, 
  "link_flair_css_class": null, 
  "author_flair_css_class": null, 
  "downs": 0, 
  "mod_reports": [], 
  "secure_media_embed": {}, 
  "saved": false, 
  "has_fetched": true, 
  "is_self": false, 
  "name": "t3_24pm00", 
  "permalink": "http://www.reddit.com/r/todayilearned/comments/24pm00/til_that_peter_cushing_who_played_the_fearsome/", 
  "stickied": false, 
  "created": 1399232829.0, 
  "url": "http://en.wikipedia.org/wiki/Grand_Moff_Tarkin#Production", 
  "author_flair_text": null, 
  "title": "TIL that Peter Cushing, who played the fearsome antagonist of Star Wars Episode IV, found the boots of his costume so uncomfortable he wore slippers and told George Lucas to avoid taking shots of his legs.", 
  "created_utc": 1399229229.0, 
  "ups": 2209, 
  "upvote_ratio": 0.91, 
  "num_comments": 190, 
  "visited": false, 
  "num_reports": null, 
  "distinguished": null
}