{
  "domain": "en.wikipedia.org", 
  "json_dict": null, 
  "banned_by": null, 
  "media_embed": {}, 
  "subreddit": "todayilearned", 
  "selftext_html": null, 
  "selftext": "", 
  "likes": null, 
  "suggested_sort": null, 
  "user_reports": [], 
  "secure_media": null, 
  "link_flair_text": null, 
  "id": "2ad4vh", 
  "gilded": 0, 
  "archived": true, 
  "clicked": false, 
  "report_reasons": null, 
  "author": "ZeroPayn", 
  "media": null, 
  "score": 3920, 
  "approved_by": null, 
  "over_18": false, 
  "hidden": false, 
  "thumbnail": "http://b.thumbs.redditmedia.com/YXlE5tkXZs8bNakw.jpg", 
  "subreddit_id": "t5_2qqjc", 
  "edited": false, 
  "link_flair_css_class": null, 
  "author_flair_css_class": null, 
  "downs": 0, 
  "mod_reports": [], 
  "secure_media_embed": {}, 
  "saved": false, 
  "has_fetched": true, 
  "is_self": false, 
  "name": "t3_2ad4vh", 
  "permalink": "http://www.reddit.com/r/todayilearned/comments/2ad4vh/til_kansas_serial_killer_the_btk_killer_installed/", 
  "stickied": false, 
  "created": 1405028350.0, 
  "url": "http://en.wikipedia.org/wiki/Dennis_Rader", 
  "author_flair_text": null, 
  "title": "TIL Kansas serial killer, the BTK Killer, installed alarms as a part of his job, and many of his clients had booked the company to stop BTK from ever entering their homes, unaware that BTK himself was installing them.", 
  "created_utc": 1405024750.0, 
  "ups": 3920, 
  "upvote_ratio": 0.96, 
  "num_comments": 1638, 
  "visited": false, 
  "num_reports": null, 
  "distinguished": null
}