{
  "domain": "en.wikipedia.org", 
  "json_dict": null, 
  "banned_by": null, 
  "media_embed": {}, 
  "subreddit": "todayilearned", 
  "selftext_html": null, 
  "selftext": "", 
  "likes": null, 
  "suggested_sort": null, 
  "user_reports": [], 
  "secure_media": null, 
  "link_flair_text": null, 
  "id": "2ew04e", 
  "gilded": 0, 
  "archived": true, 
  "clicked": false, 
  "report_reasons": null, 
  "author": "zauzau", 
  "media": null, 
  "score": 2991, 
  "approved_by": null, 
  "over_18": false, 
  "hidden": false, 
  "thumbnail": "default", 
  "subreddit_id": "t5_2qqjc", 
  "edited": false, 
  "link_flair_css_class": null, 
  "author_flair_css_class": null, 
  "downs": 0, 
  "mod_reports": [], 
  "secure_media_embed": {}, 
  "saved": false, 
  "has_fetched": true, 
  "is_self": false, 
  "name": "t3_2ew04e", 
  "permalink": "http://www.reddit.com/r/todayilearned/comments/2ew04e/til_theres_an_annual_lying_competition_in_england/", 
  "stickied": false, 
  "created": 1409287496.0, 
  "url": "http://en.wikipedia.org/wiki/World's_Biggest_Liar", 
  "author_flair_text": null, 
  "title": "TIL there's an annual lying competition in England, and competitors from around the world have five minutes to tell the biggest and most convincing lie they can. Politicians and lawyers are banned from entering because they're thought to be too good at it.", 
  "created_utc": 1409283896.0, 
  "ups": 2991, 
  "upvote_ratio": 0.93, 
  "num_comments": 109, 
  "visited": false, 
  "num_reports": null, 
  "distinguished": null
}