{
  "domain": "en.wikipedia.org", 
  "json_dict": null, 
  "banned_by": null, 
  "media_embed": {}, 
  "subreddit": "todayilearned", 
  "selftext_html": null, 
  "selftext": "", 
  "likes": null, 
  "suggested_sort": null, 
  "user_reports": [], 
  "secure_media": null, 
  "link_flair_text": null, 
  "id": "2fg3t8", 
  "gilded": 0, 
  "archived": true, 
  "clicked": false, 
  "report_reasons": null, 
  "author": "SpinningPissingRabbi", 
  "media": null, 
  "score": 1372, 
  "approved_by": null, 
  "over_18": false, 
  "hidden": false, 
  "thumbnail": "http://a.thumbs.redditmedia.com/55zN_jg86ds-wccltYKq_74Sw6j4lTDDw5gMp0fhIG0.jpg", 
  "subreddit_id": "t5_2qqjc", 
  "edited": false, 
  "link_flair_css_class": null, 
  "author_flair_css_class": null, 
  "downs": 0, 
  "mod_reports": [], 
  "secure_media_embed": {}, 
  "saved": false, 
  "has_fetched": true, 
  "is_self": false, 
  "name": "t3_2fg3t8", 
  "permalink": "http://www.reddit.com/r/todayilearned/comments/2fg3t8/til_that_in_400_bc_persian_engineers_could_store/", 
  "stickied": false, 
  "created": 1409835817.0, 
  "url": "http://en.wikipedia.org/wiki/Qanat#Applications_of_qanats", 
  "author_flair_text": null, 
  "title": "TIL that in 400 BC Persian engineers could store ice, in the desert, in the middle of summer.", 
  "created_utc": 1409832217.0, 
  "ups": 1372, 
  "upvote_ratio": 0.94, 
  "num_comments": 110, 
  "visited": false, 
  "num_reports": null, 
  "distinguished": null
}