{
  "domain": "en.wikipedia.org", 
  "json_dict": null, 
  "banned_by": null, 
  "media_embed": {}, 
  "subreddit": "todayilearned", 
  "selftext_html": null, 
  "selftext": "", 
  "likes": null, 
  "suggested_sort": null, 
  "user_reports": [], 
  "secure_media": null, 
  "link_flair_text": null, 
  "id": "278crk", 
  "gilded": 0, 
  "archived": true, 
  "clicked": false, 
  "report_reasons": null, 
  "author": "SolomonCleft", 
  "media": null, 
  "score": 1963, 
  "approved_by": null, 
  "over_18": false, 
  "hidden": false, 
  "thumbnail": "http://b.thumbs.redditmedia.com/RzS_oxMORPXgTtFg.jpg", 
  "subreddit_id": "t5_2qqjc", 
  "edited": false, 
  "link_flair_css_class": null, 
  "author_flair_css_class": null, 
  "downs": 0, 
  "mod_reports": [], 
  "secure_media_embed": {}, 
  "saved": false, 
  "has_fetched": true, 
  "is_self": false, 
  "name": "t3_278crk", 
  "permalink": "http://www.reddit.com/r/todayilearned/comments/278crk/til_that_the_aztecs_fought_with_a_macuahuitl_a/", 
  "stickied": false, 
  "created": 1401830743.0, 
  "url": "https://en.wikipedia.org/wiki/Macuahuitl#Effectiveness", 
  "author_flair_text": null, 
  "title": "TIL that the Aztecs fought with a \"Macuahuitl\" - a wooden sword embedded with prismatic blades made from obsidian, a volcanic glass stone. According to reports from Spanish conquistadors, it was sharp enough to decapitate a man and even a horse.", 
  "created_utc": 1401827143.0, 
  "ups": 1963, 
  "upvote_ratio": 0.93, 
  "num_comments": 311, 
  "visited": false, 
  "num_reports": null, 
  "distinguished": null
}