{
  "domain": "en.wikipedia.org", 
  "json_dict": null, 
  "banned_by": null, 
  "media_embed": {}, 
  "subreddit": "todayilearned", 
  "selftext_html": null, 
  "selftext": "", 
  "likes": null, 
  "suggested_sort": null, 
  "user_reports": [], 
  "secure_media": null, 
  "link_flair_text": null, 
  "id": "2dehit", 
  "gilded": 0, 
  "archived": true, 
  "clicked": false, 
  "report_reasons": null, 
  "author": "WoopAhhh", 
  "media": null, 
  "score": 1557, 
  "approved_by": null, 
  "over_18": false, 
  "hidden": false, 
  "thumbnail": "default", 
  "subreddit_id": "t5_2qqjc", 
  "edited": false, 
  "link_flair_css_class": null, 
  "author_flair_css_class": null, 
  "downs": 0, 
  "mod_reports": [], 
  "secure_media_embed": {}, 
  "saved": false, 
  "has_fetched": true, 
  "is_self": false, 
  "name": "t3_2dehit", 
  "permalink": "http://www.reddit.com/r/todayilearned/comments/2dehit/til_that_we_are_less_likely_to_be_sexually/", 
  "stickied": false, 
  "created": 1407903759.0, 
  "url": "http://en.wikipedia.org/wiki/Westermarck_effect", 
  "author_flair_text": null, 
  "title": "TIL that we are less likely to be sexually attracted to people that we grew up with early in life, due to the Westermark effect. In other words, it could be nature's way of preventing incest.", 
  "created_utc": 1407900159.0, 
  "ups": 1557, 
  "upvote_ratio": 0.92, 
  "num_comments": 64, 
  "visited": false, 
  "num_reports": null, 
  "distinguished": null
}